surrealdb_rpc/__init__.py
surrealdb_rpc/py.typed
surrealdb_rpc/client/__init__.py
surrealdb_rpc/client/interface.py
surrealdb_rpc/client/websocket/__init__.py
surrealdb_rpc/client/websocket/base.py
surrealdb_rpc/client/websocket/surrealdb.py
surrealdb_rpc/data_model/__init__.py
surrealdb_rpc/data_model/record_id.py
surrealdb_rpc/data_model/string.py
surrealdb_rpc/data_model/surql.py
surrealdb_rpc/data_model/table.py
surrealdb_rpc/data_model/thing.py
surrealdb_rpc/data_model/types/__init__.py
surrealdb_rpc/data_model/types/extension.py
surrealdb_rpc/serialization/__init__.py
surrealdb_rpc/serialization/abc.py
surrealdb_rpc/serialization/json.py
surrealdb_rpc/serialization/msgpack.py
surrealdb_rpc/tests/__init__.py
surrealdb_rpc/tests/integration/__init__.py
surrealdb_rpc/tests/integration/test_websocket.py
surrealdb_rpc/tests/unit/test_data_model.py
surrealdb_rpc-0.3.6.dist-info/METADATA
surrealdb_rpc-0.3.6.dist-info/WHEEL
surrealdb_rpc-0.3.6.dist-info/licenses/LICENSE
surrealdb_rpc-0.3.6.dist-info/RECORD
