Metadata-Version: 2.4
Name: surrealdb-rpc
Version: 0.3.6
Summary: A Python library for interacting with SurrealDB via RPC.
Project-URL: Homepage, https://github.com/manu-schaaf/surrealdb-rpc.py
Project-URL: Issues, https://github.com/manu-schaaf/surrealdb-rpc.py/issues
Author: Manuel Schaaf
License:                     GNU AFFERO GENERAL PUBLIC LICENSE
License-File: LICENSE
Requires-Python: >=3.12
Requires-Dist: msgpack>=1.1.0
Requires-Dist: requests>=2.32.3
Requires-Dist: ulid>=1.1
Requires-Dist: uuid7>=0.1.0
Requires-Dist: websockets>=14.1
